duplicate_recognition/__init__.py
duplicate_recognition/entity_algorithm.py
duplicate_recognition/field_algorythm.py
duplicate_recognition/statistics.py
duplicate_recognition/utils.py
duplicate_recognition-0.1.0.dist-info/METADATA
duplicate_recognition-0.1.0.dist-info/WHEEL
duplicate_recognition-0.1.0.dist-info/licenses/LICENSE
duplicate_recognition-0.1.0.dist-info/RECORD
