Metadata-Version: 2.4
Name: duplicate_recognition
Version: 0.1.0
Summary: This Project uses the calculation of similarities scores of a set of entities in an edge list. To allow for versatile usage, it uses dependency injection to implement it into any application.
Project-URL: Homepage, https://github.com/HeIIow2/Duplicate-Recognition
Project-URL: Issues, https://github.com/HeIIow2/Duplicate-Recognition/issues
Author-email: Hazel <Hazel.Noack@proton.me>
License: MIT License
License-File: LICENSE
Classifier: License :: OSI Approved :: MIT License
Classifier: Operating System :: OS Independent
Classifier: Programming Language :: Python :: 3
Requires-Python: >=3.8
Requires-Dist: levenshtein~=0.24.0
Requires-Dist: pycountry<=24.0.1
